generate/__init__.py
generate/generate.py
generate_passwords-0.1.3.dist-info/DESCRIPTION.rst
generate_passwords-0.1.3.dist-info/METADATA
generate_passwords-0.1.3.dist-info/RECORD
generate_passwords-0.1.3.dist-info/WHEEL
generate_passwords-0.1.3.dist-info/entry_points.txt
generate_passwords-0.1.3.dist-info/metadata.json
generate_passwords-0.1.3.dist-info/top_level.txt
tests/__init__.py
tests/test_parse_commandline.py
