Metadata-Version: 2.0
Name: generate-passwords
Version: 0.1.3
Summary: A very simple tool to generate a random password
Home-page: UNKNOWN
Author: Nicolas Bock
Author-email: nicolasbock@gmail.com
License: BSD
Platform: UNKNOWN
